NginxZhongwenWendang/README.md
NginxZhongwenWendang/__init__.py
NginxZhongwenWendang/__main__.py
NginxZhongwenWendang/file.epub
NginxZhongwenWendang/index.html
NginxZhongwenWendang/css/__init__.py
NginxZhongwenWendang/css/annotations.css
NginxZhongwenWendang/css/main.css
NginxZhongwenWendang/css/normalize.css
NginxZhongwenWendang/css/popup.css
NginxZhongwenWendang/font/__init__.py
NginxZhongwenWendang/font/fontello.eot
NginxZhongwenWendang/font/fontello.svg
NginxZhongwenWendang/font/fontello.ttf
NginxZhongwenWendang/font/fontello.woff
NginxZhongwenWendang/img/__init__.py
NginxZhongwenWendang/img/annotator-glyph-sprite.png
NginxZhongwenWendang/img/annotator-icon-sprite.png
NginxZhongwenWendang/img/apple-touch-icon.png
NginxZhongwenWendang/img/cancelfullscreen.png
NginxZhongwenWendang/img/close.png
NginxZhongwenWendang/img/fullscreen.png
NginxZhongwenWendang/img/loader.gif
NginxZhongwenWendang/img/menu-icon.png
NginxZhongwenWendang/img/save.png
NginxZhongwenWendang/img/saved.png
NginxZhongwenWendang/img/settings-s.png
NginxZhongwenWendang/img/settings.png
NginxZhongwenWendang/img/star.png
NginxZhongwenWendang/js/__init__.py
NginxZhongwenWendang/js/epub.js
NginxZhongwenWendang/js/epub.min.js
NginxZhongwenWendang/js/epub.min.map
NginxZhongwenWendang/js/hooks.min.js
NginxZhongwenWendang/js/hooks.min.map
NginxZhongwenWendang/js/reader.js
NginxZhongwenWendang/js/reader.js.map
NginxZhongwenWendang/js/reader.min.js
NginxZhongwenWendang/js/reader.min.map
NginxZhongwenWendang/js/hooks/__init__.py
NginxZhongwenWendang/js/hooks/extensions/__init__.py
NginxZhongwenWendang/js/hooks/extensions/highlight.js
NginxZhongwenWendang/js/libs/__init__.py
NginxZhongwenWendang/js/libs/jquery.min.js
NginxZhongwenWendang/js/libs/localforage.min.js
NginxZhongwenWendang/js/libs/screenfull.js
NginxZhongwenWendang/js/libs/screenfull.min.js
NginxZhongwenWendang/js/libs/zip.min.js
NginxZhongwenWendang/js/plugins/__init__.py
NginxZhongwenWendang/js/plugins/hypothesis.js
nginx_zhongwen_wendang-2024.3.5.0.dist-info/METADATA
nginx_zhongwen_wendang-2024.3.5.0.dist-info/WHEEL
nginx_zhongwen_wendang-2024.3.5.0.dist-info/entry_points.txt
nginx_zhongwen_wendang-2024.3.5.0.dist-info/top_level.txt
nginx_zhongwen_wendang-2024.3.5.0.dist-info/RECORD
